color50/__init__.py
color50/color.py
color50/colorstr.py
color50/constants.py
color50/core_functions.py
color50/csscolors.json
color50-1.0.1.dist-info/LICENSE
color50-1.0.1.dist-info/METADATA
color50-1.0.1.dist-info/WHEEL
color50-1.0.1.dist-info/top_level.txt
color50-1.0.1.dist-info/RECORD
