Metadata-Version: 2.1
Name: color50
Version: 1.0.1
Summary: A lightweight Python package for colorful output at the command line.
Author-email: Daniel Fletcher <dfletcher-mail@proton.me>
Project-URL: GitHub, https://github.com/danielthefletch/color50.git
Project-URL: Documentation, https://color50.readthedocs.io/en/latest/
Project-URL: CS50P Course Website, https://cs50.harvard.edu/python/2022/
Keywords: color50,color,console,terminal,command line,CS50,CS50P
Classifier: Intended Audience :: Developers
Classifier: Intended Audience :: Education
Classifier: License :: OSI Approved :: MIT License
Classifier: Programming Language :: Python
Classifier: Programming Language :: Python :: 3
Classifier: Topic :: Software Development :: Libraries :: Python Modules
Classifier: Topic :: System :: Console Fonts
Requires-Python: >=3.10
License-File: LICENSE
